History.rst
LICENSE.txt
MANIFEST.in
README.rst
constraints.txt
requirements.txt
requirements_read_the_docs.txt
setup.cfg
setup.py
bin/qirest
qirest/__init__.py
qirest.egg-info/PKG-INFO
qirest.egg-info/SOURCES.txt
qirest.egg-info/dependency_links.txt
qirest.egg-info/requires.txt
qirest.egg-info/top_level.txt
qirest/server/__init__.py
qirest/server/run.py
qirest/server/settings.py
qirest/server/spawn.py
qirest/test/__init__.py
qirest/test/helpers/__init__.py
qirest/test/helpers/seed.py
qirest/test/unit/__init__.py
qirest/test/unit/test_seed.py