Metadata-Version: 1.1
Name: qirest
Version: 6.2.12
Summary: Quantitative Imaging Profile REST server
Home-page: http://qirest.readthedocs.org/en/latest/
Author: OHSU Knight Cancer Institute
Author-email: loneyf@ohsu.edu
License: UNKNOWN
Platform: UNKNOWN
Classifier: Development Status :: 5 - Production/Stable
Classifier: Topic :: Scientific/Engineering :: Bio-Informatics
Classifier: Environment :: Web Environment
Classifier: Intended Audience :: Science/Research
Classifier: License :: OSI Approved :: MIT License
Classifier: Operating System :: OS Independent
Classifier: Programming Language :: Python
Classifier: Programming Language :: Python :: 2.6
Classifier: Programming Language :: Python :: 2.7
Classifier: Natural Language :: English
